latex_generator/__init__.py
latex_generator/image.py
latex_generator/latex_wrapper.py
latex_generator/tabular.py
latex_generator_example-0.1.0.dist-info/METADATA
latex_generator_example-0.1.0.dist-info/WHEEL
latex_generator_example-0.1.0.dist-info/top_level.txt
latex_generator_example-0.1.0.dist-info/RECORD
