Metadata-Version: 2.1
Name: latex-generator-example
Version: 0.1.0
Summary: Библиотека для генерации LaTeX таблиц и изображений.
Home-page: UNKNOWN
Author: Alexnadr Kozhevnikov
Author-email: alexandr.kozhevnikov8@yandex.ru
License: UNKNOWN
Platform: UNKNOWN
Classifier: Programming Language :: Python :: 3
Classifier: License :: OSI Approved :: MIT License
Classifier: Operating System :: OS Independent
Requires-Python: >=3.8
